topsis/__init__.py
topsis/__main__.py
Topsis_Paramvir_102117147-1.0.2.dist-info/METADATA
Topsis_Paramvir_102117147-1.0.2.dist-info/WHEEL
Topsis_Paramvir_102117147-1.0.2.dist-info/entry_points.txt
Topsis_Paramvir_102117147-1.0.2.dist-info/top_level.txt
Topsis_Paramvir_102117147-1.0.2.dist-info/RECORD
