Metadata-Version: 2.1
Name: Topsis-Paramvir-102117147
Version: 1.0.2
Summary: It gives the ranking to models as per the TOPSIS score.Please view the instructions so as to run the package smoothly in your terminal.
Home-page: https://github.com/Paramvir705/Topsis-Paramvir-102117147
Author: Paramvir Singh
Author-email: parampabla2u@gmail.com
License: MIT
Classifier: License :: OSI Approved :: MIT License
Classifier: Programming Language :: Python :: 3.6
Classifier: Programming Language :: Python :: 3.7
Classifier: Programming Language :: Python :: 3.8
